omc_kube/__init__.py
omc_kube/assets/__init__.py
omc_kube/assets/k8s_spec.py
omc_kube/config/__init__.py
omc_kube/config/settings.yaml
omc_kube/core/__init__.py
omc_kube/core/k8s_utils.py
omc_kube/core/k8s_utils_origin.py
omc_kube/kube/__init__.py
omc_kube/kube/kube.py
omc_kube/kube/kube_node_resource.py
omc_kube/kube/kube_resource.py
omc_kube/kube/config/__init__.py
omc_kube/kube/config/config.py
omc_kube/kube/configmap/__init__.py
omc_kube/kube/configmap/configmap.py
omc_kube/kube/configmap/node/__init__.py
omc_kube/kube/configmap/node/node.py
omc_kube/kube/deployment/__init__.py
omc_kube/kube/deployment/deployment.py
omc_kube/kube/deployment/node/__init__.py
omc_kube/kube/deployment/node/node.py
omc_kube/kube/endpoints/__init__.py
omc_kube/kube/endpoints/endpoints.py
omc_kube/kube/event/__init__.py
omc_kube/kube/event/event.py
omc_kube/kube/ingress/__init__.py
omc_kube/kube/ingress/ingress.py
omc_kube/kube/pod/__init__.py
omc_kube/kube/pod/pod.py
omc_kube/kube/pod/config/__init__.py
omc_kube/kube/pod/config/config.py
omc_kube/kube/pod/container/__init__.py
omc_kube/kube/pod/container/container.py
omc_kube/kube/pod/node/__init__.py
omc_kube/kube/pod/node/node.py
omc_kube/kube/pv/__init__.py
omc_kube/kube/pv/pv.py
omc_kube/kube/pvc/__init__.py
omc_kube/kube/pvc/pvc.py
omc_kube/kube/service/__init__.py
omc_kube/kube/service/service.py
omc_kube/service/__init__.py
omc_kube/service/kube_config_service.py
omc_kube-0.0.4.dist-info/METADATA
omc_kube-0.0.4.dist-info/WHEEL
omc_kube-0.0.4.dist-info/top_level.txt
omc_kube-0.0.4.dist-info/RECORD
